test_server/__init__.py
test_server/__main__.py
test_server/server.py
mcp_test_server-0.3.4.dist-info/METADATA
mcp_test_server-0.3.4.dist-info/WHEEL
mcp_test_server-0.3.4.dist-info/entry_points.txt
mcp_test_server-0.3.4.dist-info/RECORD
