Metadata-Version: 2.4
Name: mcp-test-server
Version: 0.3.4
Summary: A custom MCP SSE HTTP Server with parameter support
Author: MCP Demo
License-Expression: MIT
Requires-Python: >=3.10
Requires-Dist: mcp>=1.0.0
Requires-Dist: pydantic>=2.0.0
